mesmer/__init__.py
mesmer/_astropy_init.py
mesmer/conftest.py
mesmer/data/README.rst
mesmer/extern/__init__.py
mesmer/likelihood.py
mesmer/seds.py
mesmer/tests/__init__.py
mesmer/tests/test_sed.py
mesmer/tools.py
mesmer/utils/__init__.py
mesmer/utils/tests/__init__.py
mesmer-0.0.1.dist-info/WHEEL
mesmer-0.0.1.dist-info/METADATA
mesmer-0.0.1.dist-info/RECORD
